setup.py
ZotonicClient.egg-info/PKG-INFO
ZotonicClient.egg-info/SOURCES.txt
ZotonicClient.egg-info/dependency_links.txt
ZotonicClient.egg-info/entry_points.txt
ZotonicClient.egg-info/requires.txt
ZotonicClient.egg-info/top_level.txt
zclient/__init__.py
zclient/base.py
zclient/cli.py