Metadata-Version: 1.0
Name: ZotonicClient
Version: 1.0
Summary: Support library for accessing Zotonic websites from Python.
Home-page: http://github.com/arjan/zclient
Author: Arjan Scherpenisse
Author-email: arjan@scherpenisse.net
License: MIT
Keywords: zotonic api web2.0 oauth
Platform: any
Classifier: Development Status :: 3 - Alpha
Classifier: Intended Audience :: Developers
Classifier: License :: OSI Approved :: MIT License
Classifier: Programming Language :: Python
Classifier: Topic :: Software Development :: Libraries :: Python Modules
